simmeth/__init__.py
simmeth/alternative.py
simmeth/belief.py
simmeth/environment.py
simmeth/simulation.py
simmeth/strategy.py
tests/__init__.py
tests/test_main.py
simmeth-0.1.0.dist-info/LICENSE
simmeth-0.1.0.dist-info/METADATA
simmeth-0.1.0.dist-info/WHEEL
simmeth-0.1.0.dist-info/top_level.txt
simmeth-0.1.0.dist-info/RECORD
