Metadata-Version: 2.1
Name: simmeth
Version: 0.1.0
Summary: Simulation Methods Package
Home-page: https://github.com/LMU-MBR/simmeth
Author: Markus Lill
Author-email: ml.ecm.ec@som.lmu.de
License: UNKNOWN
Platform: UNKNOWN
Classifier: Programming Language :: Python :: 3
Classifier: License :: OSI Approved :: MIT License
Classifier: Operating System :: OS Independent
Requires-Python: >=3.6
License-File: LICENSE
